WorldMonitor/__init__.py
WorldMonitor/movies/__init__.py
WorldMonitor/pictures/__init__.py
WorldMonitor/sounds/__init__.py
tests/__init__.py
WorldMonitor-2023.9.1.dist-info/LICENSE.txt
WorldMonitor-2023.9.1.dist-info/METADATA
WorldMonitor-2023.9.1.dist-info/WHEEL
WorldMonitor-2023.9.1.dist-info/top_level.txt
WorldMonitor-2023.9.1.dist-info/RECORD
