Metadata-Version: 2.1
Name: WorldMonitor
Version: 2023.9.1
Summary: A package that monits the working signals and provides method to solve problems。
Home-page: https://github.com/anzechannel/WorldMonitor
Author: anzechannel
Author-email: 348834851@qq.com
Classifier: Programming Language :: Python :: 3
Classifier: License :: OSI Approved :: MIT License
Classifier: Operating System :: OS Independent
Requires-Python: >=3.10
License-File: LICENSE.txt
